bw2temporalis/__init__.py
bw2temporalis/dynamic_ia_methods.py
bw2temporalis/dynamic_lca.py
bw2temporalis/temporal_distribution.py
bw2temporalis/timeline.py
bw2temporalis/utils.py
bw2temporalis/cofire/__init__.py
bw2temporalis/cofire/constants.py
bw2temporalis/cofire/main.py
bw2temporalis/examples/__init__.py
bw2temporalis/examples/ia.py
bw2temporalis/examples/inv.py
bw2temporalis/tests/__init__.py
bw2temporalis/tests/dlca.py
bw2temporalis/tests/ia.py
bw2temporalis/tests/td.py
bw2temporalis-0.9.2.dist-info/DESCRIPTION.rst
bw2temporalis-0.9.2.dist-info/METADATA
bw2temporalis-0.9.2.dist-info/RECORD
bw2temporalis-0.9.2.dist-info/WHEEL
bw2temporalis-0.9.2.dist-info/metadata.json
bw2temporalis-0.9.2.dist-info/top_level.txt
