Metadata-Version: 2.0
Name: bw2temporalis
Version: 0.9.2
Summary: Provide a dynamic LCA calculations for the Brightway2 life cycle assessment framework
Home-page: https://bitbucket.org/cmutel/brightway2-temporalis
Author: Chris Mutel
Author-email: cmutel@gmail.com
License: Copyright (c) 2014, Chris Mutel and ETH Zürich
Requires-Dist: arrow
Requires-Dist: brightway2
Requires-Dist: bw2analyzer
Requires-Dist: bw2calc (>=0.11)
Requires-Dist: bw2data (>=0.12)
Requires-Dist: bw2speedups (>=2.0)
Requires-Dist: eight
Requires-Dist: numexpr
Requires-Dist: numpy
Requires-Dist: scipy
Requires-Dist: stats-arrays
